setup.py
dsnd_probability_miy/Binomialdistribution.py
dsnd_probability_miy/Gaussiandistribution.py
dsnd_probability_miy/Generaldistribution.py
dsnd_probability_miy/__init__.py
dsnd_probability_miy.egg-info/PKG-INFO
dsnd_probability_miy.egg-info/SOURCES.txt
dsnd_probability_miy.egg-info/dependency_links.txt
dsnd_probability_miy.egg-info/not-zip-safe
dsnd_probability_miy.egg-info/top_level.txt