Metadata-Version: 1.0
Name: dsnd-probability-miy
Version: 0.1
Summary: Gaussian and Binomial distributions
Home-page: UNKNOWN
Author: Akemi
Author-email: miyazawa.yu@hotmail.com
License: UNKNOWN
Platform: UNKNOWN
